cadens_package/__init__.py
cadens_package/core.py
cadens_package-0.2.0.dist-info/METADATA
cadens_package-0.2.0.dist-info/WHEEL
cadens_package-0.2.0.dist-info/top_level.txt
cadens_package-0.2.0.dist-info/RECORD
