Metadata-Version: 2.4
Name: cadens_package
Version: 0.2.0
Summary: A benign demo package for MITRE ATT&CK coursework.
Author-email: Caden <cncpro2014@outlook.com>
Requires-Python: >=3.7
